{
    "/js/app.js": "/js/app.js?id=f618ab06e6224ce8d9be",
    "/css/core.css": "/css/core.css?id=cde5ed6f4a48f128d8fd",
    "/css/plugins.css": "/css/plugins.css?id=3f76bdc79a5da016e89e",
    "/css/fonts/fonts.css": "/css/fonts/fonts.css?id=ded35f34695d633b112b",
    "/js/ie9.js": "/js/ie9.js?id=d1759dea5987592f8b58",
    "/js/ie10.js": "/js/ie10.js?id=0f389a33576caa8c57e9",
    "/js/header.js": "/js/header.js?id=979f7a1b91c1679dfc34",
    "/js/core.js": "/js/core.js?id=b4641218ca0e8506eade",
    "/js/plugins.js": "/js/plugins.js?id=24df64c79218a958fa7a",
    "/js/star_plugin.js": "/js/star_plugin.js?id=d41d8cd98f00b204e980",
    "/js/scripts.js": "/js/scripts.js?id=3aff9c937380d7b2f53a",
    "/js/config.js": "/js/config.js?id=1f5385e717d2c651ddc0",
    "/js/page.js": "/js/page.js?id=9a0b07058f5622fa91bb",
    "/css/utility-sortable.css": "/css/utility-sortable.css?id=afc09f50c599bbc57bc0",
    "/js/utility-sortable.js": "/js/utility-sortable.js?id=ebb2d0680ede9c32bc52",
    "/css/utility-wysiwyg.css": "/css/utility-wysiwyg.css?id=d4fb4aa466ce7448001b",
    "/js/utility-wysiwyg.js": "/js/utility-wysiwyg.js?id=d0f7cc38fa930b267160",
    "/css/dropify.css": "/css/dropify.css?id=8073bc9803c5bd841273",
    "/js/dropify.js": "/js/dropify.js?id=f32eafc79f59a03a508e",
    "/css/public.css": "/css/public.css?id=b29070652c548f98cb75",
    "/css/auth.css": "/css/auth.css?id=4f00fc038e60b46a6c58",
    "/css/error.css": "/css/error.css?id=5e081357eec916da8f53",
    "/css/summernote.ttf": "/css/summernote.ttf?id=f43ce34f9a006c5c2645",
    "/css/summernote.woff": "/css/summernote.woff?id=1b2880ac212658f460e6",
    "/css/dropify.eot": "/css/dropify.eot?id=59365accee9608310ab4",
    "/css/dropify.svg": "/css/dropify.svg?id=b321d818cc153b16e739",
    "/css/dropify.ttf": "/css/dropify.ttf?id=1bedefb14a99fb9e04fe",
    "/css/dropify.woff": "/css/dropify.woff?id=388b03d0d171d81b63ce"
}